forexcom/__init__.py
forexcom/client.py
forexcom/exceptions.py
forexcom/lightstream.py
forexcom/rest.py
forexcom/utils.py
forexcom/models/__init__.py
forexcom/models/currencies.py
forexcom/models/enums.py
forexcom/models/orders.py
forexcom/models/prices.py
forexcom/models/subscribers.py
forexcom-1.2.0.dist-info/LICENSE
forexcom-1.2.0.dist-info/METADATA
forexcom-1.2.0.dist-info/WHEEL
forexcom-1.2.0.dist-info/top_level.txt
forexcom-1.2.0.dist-info/RECORD
